[{"index":0,"picture":"http://placehold.it/32x32","age":24,"name":"Edwina Sampson","gender":"female","email":"edwinasampson@koogle.com","phone":"+1 (851) 515-3100","address":"931 Clinton Street, Healy, West Virginia, 7848","registered":"2018-04-17T09:28:49 -01:00","friends":[{"id":0,"name":"Deborah Petersen"},{"id":1,"name":"Althea Hernandez"},{"id":2,"name":"Pam Mclean"},{"id":3,"name":"Dean Donovan"},{"id":4,"name":"Mccarthy Donaldson"}]},{"index":1,"picture":"http://placehold.it/32x32","age":23,"name":"Bernard Hutchinson","gender":"male","email":"bernardhutchinson@koogle.com","phone":"+1 (932) 417-3242","address":"136 Freeman Street, Lutsen, Florida, 4088","registered":"2017-07-30T11:40:16 -01:00","friends":[{"id":0,"name":"Hall Wyatt"},{"id":1,"name":"Le Gray"},{"id":2,"name":"Candice Vaughn"},{"id":3,"name":"Booker Lancaster"},{"id":4,"name":"Chambers Beach"}]},{"index":2,"picture":"http://placehold.it/32x32","age":31,"name":"Emily Frye","gender":"female","email":"emilyfrye@koogle.com","phone":"+1 (824) 526-2623","address":"183 Lombardy Street, Boomer, Federated States Of Micronesia, 5890","registered":"2019-06-03T12:26:42 -01:00","friends":[{"id":0,"name":"Pugh Gonzalez"},{"id":1,"name":"Nicholson Trujillo"},{"id":2,"name":"Leah Reese"},{"id":3,"name":"Maritza Morris"},{"id":4,"name":"Leila Bryant"}]},{"index":3,"picture":"http://placehold.it/32x32","age":36,"name":"Meyers Dyer","gender":"male","email":"meyersdyer@koogle.com","phone":"+1 (949) 502-2486","address":"406 Joval Court, Wright, Mississippi, 6619","registered":"2017-10-16T12:16:45 -01:00","friends":[{"id":0,"name":"Willie Griffith"},{"id":1,"name":"Christensen Woodward"},{"id":2,"name":"Garza Caldwell"},{"id":3,"name":"Kaitlin Hardin"},{"id":4,"name":"Jenna Cummings"}]},{"index":4,"picture":"http://placehold.it/32x32","age":27,"name":"Morrison Burgess","gender":"male","email":"morrisonburgess@koogle.com","phone":"+1 (946) 575-2066","address":"304 Dewey Place, Carrizo, Missouri, 2074","registered":"2019-04-04T05:50:41 -01:00","friends":[{"id":0,"name":"Casey Booth"},{"id":1,"name":"Greta Dickson"},{"id":2,"name":"Neva Hebert"},{"id":3,"name":"Stafford Reed"},{"id":4,"name":"Knight Hammond"}]},{"index":5,"picture":"http://placehold.it/32x32","age":24,"name":"Tammy Schneider","gender":"female","email":"tammyschneider@koogle.com","phone":"+1 (991) 415-3307","address":"935 Heyward Street, Newkirk, Illinois, 6454","registered":"2016-03-12T04:18:04 -00:00","friends":[{"id":0,"name":"Cantu Benjamin"},{"id":1,"name":"Brittney Haney"},{"id":2,"name":"Hernandez Mercado"},{"id":3,"name":"Waller Willis"},{"id":4,"name":"Patti Murray"}]},{"index":6,"picture":"http://placehold.it/32x32","age":40,"name":"Decker Williams","gender":"male","email":"deckerwilliams@koogle.com","phone":"+1 (918) 598-2072","address":"843 Tiffany Place, Blackgum, Minnesota, 9928","registered":"2017-05-26T11:30:12 -01:00","friends":[{"id":0,"name":"Bullock Wiggins"},{"id":1,"name":"Verna Parks"},{"id":2,"name":"Earlene Hartman"},{"id":3,"name":"Lucile Briggs"},{"id":4,"name":"Moran Oneal"}]},{"index":7,"picture":"http://placehold.it/32x32","age":34,"name":"Lyons Cochran","gender":"male","email":"lyonscochran@koogle.com","phone":"+1 (862) 575-2629","address":"302 Turnbull Avenue, Sardis, Virgin Islands, 6059","registered":"2016-09-27T03:57:00 -01:00","friends":[{"id":0,"name":"Manuela Preston"},{"id":1,"name":"Velez Hamilton"},{"id":2,"name":"Grimes Franco"},{"id":3,"name":"Aida Miranda"},{"id":4,"name":"Lizzie Chaney"}]},{"index":8,"picture":"http://placehold.it/32x32","age":20,"name":"Stephanie Downs","gender":"female","email":"stephaniedowns@koogle.com","phone":"+1 (832) 559-3684","address":"724 Garland Court, Cuylerville, Oregon, 7682","registered":"2017-03-25T03:15:03 -00:00","friends":[{"id":0,"name":"Madge Benson"},{"id":1,"name":"Annmarie Foster"},{"id":2,"name":"Serena Mercer"},{"id":3,"name":"Carrie Cannon"},{"id":4,"name":"Hunter Freeman"}]},{"index":9,"picture":"http://placehold.it/32x32","age":24,"name":"Robbie Fields","gender":"female","email":"robbiefields@koogle.com","phone":"+1 (864) 493-2303","address":"246 Albemarle Road, Walland, Vermont, 5746","registered":"2017-08-10T09:10:29 -01:00","friends":[{"id":0,"name":"Bessie Warner"},{"id":1,"name":"Foster Aguilar"},{"id":2,"name":"Desiree Anthony"},{"id":3,"name":"Wolf Jacobson"},{"id":4,"name":"Britney Travis"}]},{"index":10,"picture":"http://placehold.it/32x32","age":29,"name":"Estelle Allen","gender":"female","email":"estelleallen@koogle.com","phone":"+1 (928) 578-3244","address":"284 Dank Court, Waikele, Palau, 540","registered":"2015-02-18T03:13:21 -00:00","friends":[{"id":0,"name":"Wyatt Kramer"},{"id":1,"name":"Gibson Davis"},{"id":2,"name":"Gena Randolph"},{"id":3,"name":"Combs Ballard"},{"id":4,"name":"Ashley Thornton"}]}] 
